{
  "capability": {
    "name": "id.generate",
    "version": "1.0.0",
    "category": "platform",
    "title": {
      "en": "Generate Id",
      "zh_CN": "生成标识"
    },
    "summary": {
      "en": "Allocate one or more unique identifiers using a server-side scheme.",
      "zh_CN": "按服务端方案分配一个或多个唯一标识。"
    },
    "lifecycle": "draft"
  },
  "type": "service",
  "signature": {
    "model": "request-response",
    "requestSchema": "schemas/request.json",
    "responseSchema": "schemas/response.json",
    "errorSchema": "schemas/error.json"
  },
  "semantics": {
    "idempotent": false,
    "sideEffect": true,
    "transactional": false
  },
  "examples": [
    "examples/success.json",
    "examples/failure.json"
  ],
  "tests": {
    "contractTests": "tests/contract-tests.yaml"
  }
}
